snip/__init__.py
snip/__main__.py
snip/commands.py
snip/configuration.py
snip/main.py
snip/snippet.py
snip/utilities.py
snip/repository/__init__.py
snip/repository/base.py
snip/repository/github.py
snip/repository/local.py
snipped/__init__.py
snipped/__main__.py
snipped/commands.py
snipped/configuration.py
snipped/main.py
snipped/snippet.py
snipped/utilities.py
snipped/repository/__init__.py
snipped/repository/base.py
snipped/repository/github.py
snipped/repository/local.py
snipped-0.1a3.dist-info/METADATA
snipped-0.1a3.dist-info/RECORD
snipped-0.1a3.dist-info/WHEEL
snipped-0.1a3.dist-info/entry_points.txt
snipped-0.1a3.dist-info/top_level.txt
