Metadata-Version: 2.1
Name: snipped
Version: 0.1a3
Summary: A small snippets manager.
Home-page: https://github.com/dexpota/snip
Author: Fabrizio Destro
Author-email: destro.fabrizio@gmail.com
License: UNKNOWN
Platform: UNKNOWN
Classifier: Programming Language :: Python :: 3.5
Requires-Python: >=3.5
Requires-Dist: docopt
Requires-Dist: pyyaml
Requires-Dist: pygments
Requires-Dist: requests
